README.rst
setup.py
./__init__.py
./tmp/__init__.py
./tmp/test_zip2tar.py
ruamel.zip2tar.egg-info/PKG-INFO
ruamel.zip2tar.egg-info/SOURCES.txt
ruamel.zip2tar.egg-info/dependency_links.txt
ruamel.zip2tar.egg-info/entry_points.txt
ruamel.zip2tar.egg-info/namespace_packages.txt
ruamel.zip2tar.egg-info/requires.txt
ruamel.zip2tar.egg-info/top_level.txt
test/test_zip2tar.py