Metadata-Version: 1.1
Name: ruamel.zip2tar
Version: 0.4
Summary: zip2tar, a zipfile to tar convertor without intermediate
Home-page: https://bitbucket.org/ruamel/zip2tar
Author: Anthon van der Neut
Author-email: a.van.der.neut@ruamel.eu
License: MIT license
Platform: UNKNOWN
Classifier: Development Status :: 4 - Beta
Classifier: Intended Audience :: Developers
Classifier: License :: OSI Approved :: MIT License
Classifier: Operating System :: OS Independent
Classifier: Programming Language :: Python :: 3
